ceilometer_infoblox/__init__.py
ceilometer_infoblox/discovery.py
ceilometer_infoblox/inspector/__init__.py
ceilometer_infoblox/pollsters/__init__.py
ceilometer_infoblox/pollsters/dhcp.py
ceilometer_infoblox/pollsters/dns.py
ceilometer_infoblox/tests/__init__.py
ceilometer_infoblox/tests/base.py
ceilometer_infoblox/tests/test_ceilometer_infoblox.py
ceilometer_infoblox-2.0.0.dist-info/DESCRIPTION.rst
ceilometer_infoblox-2.0.0.dist-info/METADATA
ceilometer_infoblox-2.0.0.dist-info/RECORD
ceilometer_infoblox-2.0.0.dist-info/WHEEL
ceilometer_infoblox-2.0.0.dist-info/entry_points.txt
ceilometer_infoblox-2.0.0.dist-info/metadata.json
ceilometer_infoblox-2.0.0.dist-info/pbr.json
ceilometer_infoblox-2.0.0.dist-info/top_level.txt
