Metadata-Version: 2.0
Name: ceilometer-infoblox
Version: 2.0.0
Summary: Infoblox custom meters for Ceilometer (Liberty)
Home-page: https://github.com/infobloxopen/ceilometer-infoblox
Author: Infoblox, Inc.
Author-email: openstack-maintainer@infoblox.com
License: UNKNOWN
Platform: UNKNOWN
Classifier: Environment :: OpenStack
Classifier: Intended Audience :: Information Technology
Classifier: Intended Audience :: System Administrators
Classifier: License :: OSI Approved :: Apache Software License
Classifier: Operating System :: POSIX :: Linux
Classifier: Programming Language :: Python
Classifier: Programming Language :: Python :: 2
Classifier: Programming Language :: Python :: 2.7
Requires-Dist: oslo.config (>=2.3.0)
Requires-Dist: pbr (>=1.6)
Requires-Dist: pysnmp (>=4.2.1,<5.0.0)
